smart_constants.py
SmartConstants-1.2.0.dist-info/LICENSE.txt
SmartConstants-1.2.0.dist-info/METADATA
SmartConstants-1.2.0.dist-info/WHEEL
SmartConstants-1.2.0.dist-info/top_level.txt
SmartConstants-1.2.0.dist-info/RECORD
