Metadata-Version: 2.1
Name: SmartConstants
Version: 1.2.0
Summary: magic class to declare easy-to-use "enum"-like values
Home-page: https://github.com/FelixSchwarz/smartconstants/
Author: Felix Schwarz
Author-email: felix.schwarz@oss.schwarz.eu
License: MIT
Platform: UNKNOWN
Classifier: Development Status :: 5 - Production/Stable
Classifier: Intended Audience :: Developers
Classifier: License :: OSI Approved :: MIT License
Classifier: Operating System :: OS Independent
Classifier: Programming Language :: Python
Classifier: Programming Language :: Python :: 2
Classifier: Programming Language :: Python :: 3
Classifier: Topic :: Software Development :: Libraries :: Python Modules
Requires-Dist: six
